{"AddSub_1614":{"summary":{"iterations":8,"stop_reason":{"Other":"Found equivalence"},"egraph_nodes":862,"egraph_classes":176,"memo_size":1107,"rebuilds":62,"total_time":0.004483109,"search_time":0.0022154030000000003,"apply_time":0.0019773190000000004,"rebuild_time":0.000288765},"iteration_info":[{"egraph_nodes":15,"egraph_classes":14,"applied":{"add.commute":1,"bw_0":1,"add_eq_prec":1,"diff_left_eq_prec":1,"diff_right_eq_prec":2,"add_as_xor_and":1,"sub_to_neg":2,"gt-lt":1},"hook_time":0.000015235,"search_time":0.000024714,"apply_time":0.000037344,"rebuild_time":5.613e-6,"total_time":0.000067798,"data":null,"n_rebuilds":2,"stop_reason":null},{"egraph_nodes":37,"egraph_classes":24,"applied":{"add.commute":4,"mult.commute":3,"mult_2":1,"add_0":1,"add_eq_prec":2,"diff_left_eq_prec":1,"diff_right_eq_prec":2,"add_as_xor_and":1,"xor_as_or_and":1,"Num.ring_1_class.mult_minus1-rev":2,"sub_to_neg":3},"hook_time":0.000014362,"search_time":0.000045585,"apply_time":0.000071288,"rebuild_time":7.671e-6,"total_time":0.000124607,"data":null,"n_rebuilds":2,"stop_reason":null},{"egraph_nodes":70,"egraph_classes":33,"applied":{"add.commute":5,"add.assoc":1,"mult.commute":3,"mult_2":1,"add_0":1,"add_eq_prec":2,"diff_right_eq_prec":2,"mul_eq_prec":1,"xor_as_or_and":1,"int_distrib":5,"Num.ring_1_class.mult_minus1-rev":2,"sub_to_neg":4},"hook_time":0.000014218,"search_time":0.000063401,"apply_time":0.00009806,"rebuild_time":9.13e-6,"total_time":0.000170646,"data":null,"n_rebuilds":0,"stop_reason":null},{"egraph_nodes":110,"egraph_classes":44,"applied":{"add.commute":8,"add.assoc":9,"mult.commute":7,"diff_right_eq_prec":2,"add_as_xor_and":1,"int_distrib":6,"Num.ring_1_class.mult_minus1-rev":7,"sub_to_neg":3,"sub_to_neg-rev":5},"hook_time":0.00001424,"search_time":0.000097755,"apply_time":0.00015755,"rebuild_time":0.000013585,"total_time":0.000268991,"data":null,"n_rebuilds":0,"stop_reason":null},{"egraph_nodes":177,"egraph_classes":63,"applied":{"add.commute":23,"add.assoc":40,"mult.commute":7,"mult.assoc":4,"mult_2":1,"add_0":1,"xor_as_or_and":1,"int_distrib":7,"int_distrib-rev":1,"Num.ring_1_class.mult_minus1-rev":6,"sub_to_neg":2,"sub_to_neg-rev":9},"hook_time":0.000015029,"search_time":0.000149848,"apply_time":0.000273163,"rebuild_time":0.000027404,"total_time":0.000450532,"data":null,"n_rebuilds":2,"stop_reason":null},{"egraph_nodes":321,"egraph_classes":100,"applied":{"add.commute":71,"add.assoc":138,"mult.commute":10,"mult.assoc":1,"add_0":2,"add_as_xor_and":1,"int_distrib":11,"int_distrib-rev":1,"Num.ring_1_class.mult_minus1-rev":5,"sub_to_neg":1,"sub_to_neg-rev":28},"hook_time":0.0000151,"search_time":0.000254862,"apply_time":0.000605242,"rebuild_time":0.00007506,"total_time":0.000935263,"data":null,"n_rebuilds":14,"stop_reason":null},{"egraph_nodes":710,"egraph_classes":202,"applied":{"add.commute":220,"mult.commute":7,"mult.assoc":4,"mult_2":1,"diff_self":1,"add_0":4,"mult_1":1,"diff_right_eq_prec":1,"add_as_xor_and":2,"xor_as_or_and":2,"int_distrib":23,"int_distrib-rev":4,"Num.ring_1_class.mult_minus1-rev":5,"sub_to_neg":4,"sub_to_neg-rev":72},"hook_time":0.000015823,"search_time":0.001579184,"apply_time":0.000734571,"rebuild_time":0.00009602,"total_time":0.002410004,"data":null,"n_rebuilds":42,"stop_reason":null},{"egraph_nodes":1107,"egraph_classes":176,"applied":{},"hook_time":0.000030152,"search_time":5.4e-8,"apply_time":1.01e-7,"rebuild_time":0.000054282,"total_time":0.000055268,"data":null,"n_rebuilds":0,"stop_reason":{"Other":"Found equivalence"}}]},"Select_1105":{"summary":{"iterations":1,"stop_reason":{"Other":"Found equivalence"},"egraph_nodes":6,"egraph_classes":5,"memo_size":6,"rebuilds":0,"total_time":1.06e-6,"search_time":5.9e-8,"apply_time":7.9e-8,"rebuild_time":6.4e-7},"iteration_info":[{"egraph_nodes":6,"egraph_classes":5,"applied":{},"hook_time":5.446e-6,"search_time":5.9e-8,"apply_time":7.9e-8,"rebuild_time":6.4e-7,"total_time":1.06e-6,"data":null,"n_rebuilds":0,"stop_reason":{"Other":"Found equivalence"}}]},"AddSub_1176":{"summary":{"iterations":3,"stop_reason":{"Other":"Found equivalence"},"egraph_nodes":56,"egraph_classes":28,"memo_size":76,"rebuilds":13,"total_time":0.000173319,"search_time":0.000055397000000000005,"apply_time":0.00009919800000000001,"rebuild_time":0.000018236},"iteration_info":[{"egraph_nodes":15,"egraph_classes":14,"applied":{"add.commute":1,"bw_0":1,"add_eq_prec":1,"diff_left_eq_prec":1,"diff_right_eq_prec":2,"add_as_xor_and":1,"sub_to_neg":2,"gt-lt":1},"hook_time":0.000014957,"search_time":0.000022611,"apply_time":0.000032542,"rebuild_time":4.898e-6,"total_time":0.00006021,"data":null,"n_rebuilds":2,"stop_reason":null},{"egraph_nodes":36,"egraph_classes":23,"applied":{"add.commute":4,"mult.commute":2,"mult_2":1,"add_0":1,"add_eq_prec":3,"diff_left_eq_prec":1,"add_as_xor_and":3,"xor_as_or_and":2,"Num.ring_1_class.mult_minus1-rev":1,"sub_to_neg":3},"hook_time":0.000012809,"search_time":0.000032751,"apply_time":0.000066616,"rebuild_time":0.000010729,"total_time":0.000110172,"data":null,"n_rebuilds":11,"stop_reason":null},{"egraph_nodes":76,"egraph_classes":28,"applied":{},"hook_time":0.000012291,"search_time":3.5e-8,"apply_time":4e-8,"rebuild_time":2.609e-6,"total_time":2.937e-6,"data":null,"n_rebuilds":0,"stop_reason":{"Other":"Found equivalence"}}]},"AddSub_1619":{"summary":{"iterations":6,"stop_reason":{"Other":"Found equivalence"},"egraph_nodes":266,"egraph_classes":78,"memo_size":332,"rebuilds":14,"total_time":0.0006451660000000001,"search_time":0.00020835599999999998,"apply_time":0.00039127399999999994,"rebuild_time":0.000045099},"iteration_info":[{"egraph_nodes":15,"egraph_classes":14,"applied":{"bw_0":1,"diff_left_eq_prec":2,"diff_right_eq_prec":3,"sub_to_neg":3,"gt-lt":1},"hook_time":8.531e-6,"search_time":0.000013086,"apply_time":0.00001875,"rebuild_time":2.876e-6,"total_time":0.000034769,"data":null,"n_rebuilds":2,"stop_reason":null},{"egraph_nodes":34,"egraph_classes":21,"applied":{"add.commute":3,"mult.commute":2,"add_0":1,"add_eq_prec":4,"diff_left_eq_prec":6,"Num.ring_1_class.mult_minus1-rev":2,"sub_to_neg":5},"hook_time":8.276e-6,"search_time":0.000021383,"apply_time":0.00004063,"rebuild_time":3.931e-6,"total_time":0.000066002,"data":null,"n_rebuilds":1,"stop_reason":null},{"egraph_nodes":67,"egraph_classes":30,"applied":{"add.commute":7,"add.assoc":6,"mult.commute":2,"add_0":1,"add_eq_prec":6,"diff_left_eq_prec":2,"mul_eq_prec":1,"Num.ring_1_class.mult_minus1-rev":2,"sub_to_neg":6},"hook_time":7.763e-6,"search_time":0.000037523,"apply_time":0.000059648,"rebuild_time":5.139e-6,"total_time":0.000102344,"data":null,"n_rebuilds":0,"stop_reason":null},{"egraph_nodes":106,"egraph_classes":35,"applied":{"add.commute":16,"add.assoc":24,"add_0":1,"add_as_xor_and":2,"int_distrib-rev":2,"sub_to_neg":2,"sub_to_neg-rev":3},"hook_time":7.571e-6,"search_time":0.000054983,"apply_time":0.000095273,"rebuild_time":8.593e-6,"total_time":0.000158905,"data":null,"n_rebuilds":2,"stop_reason":null},{"egraph_nodes":172,"egraph_classes":49,"applied":{"add.commute":32,"add.assoc":57,"mult.commute":4,"mult_2":2,"diff_self":1,"add_0":2,"add_as_xor_and":2,"xor_as_or_and":2,"int_distrib":1,"int_distrib-rev":2,"Num.ring_1_class.mult_minus1-rev":2,"sub_to_neg-rev":14},"hook_time":8.358e-6,"search_time":0.000081362,"apply_time":0.000176947,"rebuild_time":0.000018779,"total_time":0.000277139,"data":null,"n_rebuilds":9,"stop_reason":null},{"egraph_nodes":332,"egraph_classes":78,"applied":{},"hook_time":8.229e-6,"search_time":1.9e-8,"apply_time":2.6e-8,"rebuild_time":5.781e-6,"total_time":6.007e-6,"data":null,"n_rebuilds":0,"stop_reason":{"Other":"Found equivalence"}}]},"Select_1100":{"summary":{"iterations":1,"stop_reason":{"Other":"Found equivalence"},"egraph_nodes":6,"egraph_classes":5,"memo_size":6,"rebuilds":0,"total_time":4.98e-7,"search_time":2e-8,"apply_time":3.9e-8,"rebuild_time":2.99e-7},"iteration_info":[{"egraph_nodes":6,"egraph_classes":5,"applied":{},"hook_time":2.748e-6,"search_time":2e-8,"apply_time":3.9e-8,"rebuild_time":2.99e-7,"total_time":4.98e-7,"data":null,"n_rebuilds":0,"stop_reason":{"Other":"Found equivalence"}}]},"muldivrem_290_292":{"summary":{"iterations":3,"stop_reason":{"Other":"Found equivalence"},"egraph_nodes":33,"egraph_classes":18,"memo_size":40,"rebuilds":4,"total_time":0.000156372,"search_time":0.00006334500000000001,"apply_time":0.000078917,"rebuild_time":0.000013531},"iteration_info":[{"egraph_nodes":19,"egraph_classes":17,"applied":{"mult.commute":1,"bw_1":1,"mul_eq_prec":1,"shl_def":2,"gt-lt":1,"gt-lt-rev":1},"hook_time":0.000021593,"search_time":0.000028703,"apply_time":0.000025522,"rebuild_time":5.065e-6,"total_time":0.000059455,"data":null,"n_rebuilds":0,"stop_reason":null},{"egraph_nodes":29,"egraph_classes":19,"applied":{"mult.commute":3,"mult.assoc":1,"mult_1":1,"mul_eq_prec":3},"hook_time":0.000018064,"search_time":0.000034584,"apply_time":0.000053338,"rebuild_time":6.416e-6,"total_time":0.000094462,"data":null,"n_rebuilds":4,"stop_reason":null},{"egraph_nodes":40,"egraph_classes":18,"applied":{},"hook_time":0.000016891,"search_time":5.8e-8,"apply_time":5.7e-8,"rebuild_time":2.05e-6,"total_time":2.455e-6,"data":null,"n_rebuilds":0,"stop_reason":{"Other":"Found equivalence"}}]},"muldivrem_239":{"summary":{"iterations":9,"stop_reason":{"Other":"Found equivalence"},"egraph_nodes":930,"egraph_classes":191,"memo_size":1206,"rebuilds":38,"total_time":0.007288016,"search_time":0.0028884120000000004,"apply_time":0.004021227,"rebuild_time":0.000376069},"iteration_info":[{"egraph_nodes":17,"egraph_classes":16,"applied":{"mult.commute":2,"bw_0":1,"diff_left_eq_prec":2,"diff_right_eq_prec":2,"mul_eq_prec":2,"sub_to_neg":2,"gt-lt":1},"hook_time":0.000022853,"search_time":0.000034427,"apply_time":0.000048085,"rebuild_time":8.281e-6,"total_time":0.000090974,"data":null,"n_rebuilds":4,"stop_reason":null},{"egraph_nodes":39,"egraph_classes":22,"applied":{"add.commute":2,"mult.commute":4,"add_0":2,"mul_eq_prec":4,"Num.ring_1_class.mult_minus1-rev":2,"sub_to_neg":2},"hook_time":0.000020433,"search_time":0.00004992,"apply_time":0.000090176,"rebuild_time":0.00001567,"total_time":0.000155902,"data":null,"n_rebuilds":4,"stop_reason":null},{"egraph_nodes":65,"egraph_classes":26,"applied":{"add.commute":2,"mult.commute":6,"mult.assoc":4,"add_0":2,"mul_eq_prec":3,"int_distrib":2,"Num.ring_1_class.mult_minus1-rev":2},"hook_time":0.000020158,"search_time":0.000075071,"apply_time":0.000140976,"rebuild_time":0.000010836,"total_time":0.000227035,"data":null,"n_rebuilds":4,"stop_reason":null},{"egraph_nodes":99,"egraph_classes":32,"applied":{"add.assoc":1,"mult.commute":12,"mult.assoc":8,"mul_eq_prec":4,"add_as_xor_and":1,"int_distrib":11,"Num.ring_1_class.mult_minus1-rev":4,"sub_to_neg-rev":1},"hook_time":0.000019554,"search_time":0.000119326,"apply_time":0.000237414,"rebuild_time":0.00001386,"total_time":0.000370705,"data":null,"n_rebuilds":0,"stop_reason":null},{"egraph_nodes":157,"egraph_classes":48,"applied":{"add.commute":1,"add.assoc":9,"mult.commute":19,"mult.assoc":16,"mult_2":1,"mult_0":1,"xor_as_or_and":1,"int_distrib":29,"int_distrib-rev":1,"Num.ring_1_class.mult_minus1-rev":5,"sub_to_neg":1,"sub_to_neg-rev":5},"hook_time":0.000020248,"search_time":0.000192193,"apply_time":0.000372995,"rebuild_time":0.00002534,"total_time":0.000590668,"data":null,"n_rebuilds":0,"stop_reason":null},{"egraph_nodes":270,"egraph_classes":71,"applied":{"add.commute":14,"add.assoc":60,"mult.commute":36,"mult.assoc":31,"mult_0":3,"add_as_xor_and":1,"int_distrib":96,"int_distrib-rev":22,"Num.ring_1_class.mult_minus1-rev":7,"sub_to_neg":5,"sub_to_neg-rev":29},"hook_time":0.000021557,"search_time":0.0003611,"apply_time":0.001091277,"rebuild_time":0.000090589,"total_time":0.001543153,"data":null,"n_rebuilds":6,"stop_reason":null},{"egraph_nodes":753,"egraph_classes":228,"applied":{"add.commute":159,"mult.commute":119,"mult_2":1,"add_0":11,"mult_0":5,"add_as_xor_and":5,"xor_as_or_and":1,"Num.ring_1_class.mult_minus1-rev":19,"sub_to_neg-rev":76},"hook_time":0.000022959,"search_time":0.001290534,"apply_time":0.001302352,"rebuild_time":0.000112481,"total_time":0.002705557,"data":null,"n_rebuilds":17,"stop_reason":null},{"egraph_nodes":1138,"egraph_classes":199,"applied":{"add.commute":5,"mult.commute":5,"mult_2":5,"add_0":10,"mult_1":1,"xor_as_or_and":5,"sub_to_neg":4,"sub_to_neg-rev":25},"hook_time":0.00002363,"search_time":0.000765782,"apply_time":0.000737833,"rebuild_time":0.00006608,"total_time":0.001569884,"data":null,"n_rebuilds":3,"stop_reason":null},{"egraph_nodes":1206,"egraph_classes":191,"applied":{},"hook_time":0.00002105,"search_time":5.9e-8,"apply_time":1.19e-7,"rebuild_time":0.000032932,"total_time":0.000034138,"data":null,"n_rebuilds":0,"stop_reason":{"Other":"Found equivalence"}}]},"AddSub_1574":{"summary":{"iterations":4,"stop_reason":{"Other":"Found equivalence"},"egraph_nodes":153,"egraph_classes":63,"memo_size":167,"rebuilds":3,"total_time":0.000639309,"search_time":0.00021123300000000002,"apply_time":0.00038395300000000003,"rebuild_time":0.000043293},"iteration_info":[{"egraph_nodes":18,"egraph_classes":17,"applied":{"add.commute":1,"add_eq_prec":1,"diff_left_eq_prec":3,"diff_right_eq_prec":3,"add_as_xor_and":1,"sub_to_neg":3,"gt-lt":1},"hook_time":0.000021978,"search_time":0.000037668,"apply_time":0.000055327,"rebuild_time":5.961e-6,"total_time":0.00009913,"data":null,"n_rebuilds":0,"stop_reason":null},{"egraph_nodes":46,"egraph_classes":32,"applied":{"add.commute":5,"mult.commute":4,"mult_2":1,"add_eq_prec":6,"diff_left_eq_prec":7,"diff_right_eq_prec":2,"add_as_xor_and":1,"xor_as_or_and":1,"Num.ring_1_class.mult_minus1-rev":3,"sub_to_neg":6},"hook_time":0.000019541,"search_time":0.000055826,"apply_time":0.000140922,"rebuild_time":0.00001119,"total_time":0.000208064,"data":null,"n_rebuilds":0,"stop_reason":null},{"egraph_nodes":101,"egraph_classes":51,"applied":{"add.commute":10,"add.assoc":5,"mult.commute":4,"mult_2":1,"add_eq_prec":8,"diff_left_eq_prec":2,"diff_right_eq_prec":2,"xor_as_or_and":1,"int_distrib":5,"Num.ring_1_class.mult_minus1-rev":3,"sub_to_neg":10},"hook_time":0.000021808,"search_time":0.000117694,"apply_time":0.000187649,"rebuild_time":0.000018925,"total_time":0.000324414,"data":null,"n_rebuilds":3,"stop_reason":null},{"egraph_nodes":167,"egraph_classes":63,"applied":{},"hook_time":0.000022069,"search_time":4.5e-8,"apply_time":5.5e-8,"rebuild_time":7.217e-6,"total_time":7.701e-6,"data":null,"n_rebuilds":0,"stop_reason":{"Other":"Found equivalence"}}]},"InstCombineShift497d":{"summary":{"iterations":5,"stop_reason":{"Other":"Found equivalence"},"egraph_nodes":157,"egraph_classes":68,"memo_size":160,"rebuilds":1,"total_time":0.0008688499999999999,"search_time":0.00030521099999999995,"apply_time":0.000517791,"rebuild_time":0.000045057},"iteration_info":[{"egraph_nodes":23,"egraph_classes":21,"applied":{"add.commute":2,"add_eq_prec":2,"shl_def":3,"add_as_xor_and":2,"gt-lt":1,"gt-lt-rev":1},"hook_time":0.000027305,"search_time":0.000033791,"apply_time":0.000039477,"rebuild_time":5.241e-6,"total_time":0.000078662,"data":null,"n_rebuilds":0,"stop_reason":null},{"egraph_nodes":44,"egraph_classes":31,"applied":{"add.commute":4,"mult.commute":5,"mult_2":2,"add_eq_prec":2,"mul_eq_prec":4,"add_as_xor_and":2,"xor_as_or_and":2},"hook_time":0.000026001,"search_time":0.000050117,"apply_time":0.000112293,"rebuild_time":8.201e-6,"total_time":0.000170703,"data":null,"n_rebuilds":0,"stop_reason":null},{"egraph_nodes":79,"egraph_classes":45,"applied":{"add.commute":4,"add.assoc":2,"mult.commute":6,"mult_2":2,"add_eq_prec":5,"mul_eq_prec":1,"xor_as_or_and":2,"sub_to_neg":2},"hook_time":0.000026059,"search_time":0.000087566,"apply_time":0.00017982,"rebuild_time":9.998e-6,"total_time":0.000277508,"data":null,"n_rebuilds":0,"stop_reason":null},{"egraph_nodes":116,"egraph_classes":58,"applied":{"add.commute":11,"add.assoc":4,"mult.commute":3,"add_eq_prec":1,"mul_eq_prec":1,"int_distrib":8,"int_distrib-rev":1,"Num.ring_1_class.mult_minus1-rev":2,"sub_to_neg":2},"hook_time":0.000025715,"search_time":0.000133673,"apply_time":0.000186163,"rebuild_time":0.000014729,"total_time":0.000334687,"data":null,"n_rebuilds":1,"stop_reason":null},{"egraph_nodes":160,"egraph_classes":68,"applied":{},"hook_time":0.000025522,"search_time":6.4e-8,"apply_time":3.8e-8,"rebuild_time":6.888e-6,"total_time":7.29e-6,"data":null,"n_rebuilds":0,"stop_reason":{"Other":"Found equivalence"}}]},"muldivrem_152":{"summary":{"iterations":3,"stop_reason":{"Other":"Found equivalence"},"egraph_nodes":27,"egraph_classes":13,"memo_size":32,"rebuilds":4,"total_time":0.00015518499999999999,"search_time":0.000059054,"apply_time":0.00008430699999999999,"rebuild_time":0.000011248000000000001},"iteration_info":[{"egraph_nodes":13,"egraph_classes":12,"applied":{"mult.commute":1,"bw_0":1,"diff_right_eq_prec":1,"mul_eq_prec":1,"sub_to_neg":1,"gt-lt":1},"hook_time":0.000015339,"search_time":0.000026993,"apply_time":0.000031869,"rebuild_time":4.509e-6,"total_time":0.000063545,"data":null,"n_rebuilds":2,"stop_reason":null},{"egraph_nodes":23,"egraph_classes":14,"applied":{"add.commute":1,"mult.commute":2,"add_0":1,"mul_eq_prec":1,"Num.ring_1_class.mult_minus1-rev":1,"sub_to_neg":1},"hook_time":0.000012581,"search_time":0.000032022,"apply_time":0.000052371,"rebuild_time":4.957e-6,"total_time":0.000089428,"data":null,"n_rebuilds":2,"stop_reason":null},{"egraph_nodes":32,"egraph_classes":13,"applied":{},"hook_time":0.0000116,"search_time":3.9e-8,"apply_time":6.7e-8,"rebuild_time":1.782e-6,"total_time":2.212e-6,"data":null,"n_rebuilds":0,"stop_reason":{"Other":"Found equivalence"}}]},"AddSub_1539_2":{"summary":{"iterations":3,"stop_reason":{"Other":"Found equivalence"},"egraph_nodes":47,"egraph_classes":26,"memo_size":48,"rebuilds":0,"total_time":0.000165539,"search_time":0.000061589,"apply_time":0.00009131399999999999,"rebuild_time":0.000012077},"iteration_info":[{"egraph_nodes":14,"egraph_classes":13,"applied":{"add.commute":1,"add_eq_prec":1,"diff_left_eq_prec":1,"diff_right_eq_prec":1,"add_as_xor_and":1,"Num.ring_1_class.mult_minus1":1,"sub_to_neg":1,"gt-lt":1},"hook_time":0.000018849,"search_time":0.000025611,"apply_time":0.000032395,"rebuild_time":3.685e-6,"total_time":0.000061846,"data":null,"n_rebuilds":0,"stop_reason":null},{"egraph_nodes":30,"egraph_classes":21,"applied":{"add.commute":3,"mult.commute":2,"mult_2":1,"add_eq_prec":2,"diff_left_eq_prec":1,"add_as_xor_and":1,"xor_as_or_and":1,"sub_to_neg":2},"hook_time":0.000015763,"search_time":0.000035931,"apply_time":0.000058877,"rebuild_time":5.48e-6,"total_time":0.000100388,"data":null,"n_rebuilds":0,"stop_reason":null},{"egraph_nodes":48,"egraph_classes":26,"applied":{},"hook_time":0.000014895,"search_time":4.7e-8,"apply_time":4.2e-8,"rebuild_time":2.912e-6,"total_time":3.305e-6,"data":null,"n_rebuilds":0,"stop_reason":{"Other":"Found equivalence"}}]},"AddSub_1165":{"summary":{"iterations":4,"stop_reason":{"Other":"Found equivalence"},"egraph_nodes":156,"egraph_classes":60,"memo_size":187,"rebuilds":19,"total_time":0.000790824,"search_time":0.000244258,"apply_time":0.000484926,"rebuild_time":0.000060839},"iteration_info":[{"egraph_nodes":19,"egraph_classes":18,"applied":{"add.commute":2,"bw_0":1,"add_eq_prec":2,"diff_left_eq_prec":3,"diff_right_eq_prec":3,"add_as_xor_and":2,"sub_to_neg":3,"gt-lt":1},"hook_time":0.000026659,"search_time":0.000037137,"apply_time":0.000059932,"rebuild_time":0.000013197,"total_time":0.000110412,"data":null,"n_rebuilds":5,"stop_reason":null},{"egraph_nodes":56,"egraph_classes":33,"applied":{"add.commute":7,"add.assoc":1,"mult.commute":5,"mult_2":2,"add_0":3,"add_eq_prec":4,"diff_right_eq_prec":1,"add_as_xor_and":2,"xor_as_or_and":2,"Num.ring_1_class.mult_minus1-rev":3,"sub_to_neg":3},"hook_time":0.000025111,"search_time":0.000082597,"apply_time":0.000177151,"rebuild_time":0.000018952,"total_time":0.000278834,"data":null,"n_rebuilds":7,"stop_reason":null},{"egraph_nodes":113,"egraph_classes":46,"applied":{"add.commute":10,"add.assoc":7,"mult.commute":5,"mult_2":2,"add_0":3,"add_eq_prec":3,"diff_right_eq_prec":1,"mul_eq_prec":3,"xor_as_or_and":2,"int_distrib":5,"Num.ring_1_class.mult_minus1-rev":3,"sub_to_neg":3,"sub_to_neg-rev":1},"hook_time":0.000026159,"search_time":0.000124484,"apply_time":0.000247781,"rebuild_time":0.000021104,"total_time":0.0003935,"data":null,"n_rebuilds":7,"stop_reason":null},{"egraph_nodes":187,"egraph_classes":60,"applied":{},"hook_time":0.000024486,"search_time":4e-8,"apply_time":6.2e-8,"rebuild_time":7.586e-6,"total_time":8.078e-6,"data":null,"n_rebuilds":0,"stop_reason":{"Other":"Found equivalence"}}]},"muldivrem_229":{"summary":{"iterations":4,"stop_reason":{"Other":"Found equivalence"},"egraph_nodes":138,"egraph_classes":66,"memo_size":139,"rebuilds":1,"total_time":0.000712963,"search_time":0.000212617,"apply_time":0.000465611,"rebuild_time":0.000033969000000000006},"iteration_info":[{"egraph_nodes":20,"egraph_classes":19,"applied":{"add.commute":2,"mult.commute":3,"add_eq_prec":2,"mul_eq_prec":3,"add_as_xor_and":2,"gt-lt":1},"hook_time":0.000027219,"search_time":0.000045553,"apply_time":0.00006233,"rebuild_time":6.257e-6,"total_time":0.000114303,"data":null,"n_rebuilds":0,"stop_reason":null},{"egraph_nodes":45,"egraph_classes":31,"applied":{"add.commute":4,"mult.commute":5,"mult_2":2,"add_eq_prec":4,"mul_eq_prec":4,"add_as_xor_and":2,"xor_as_or_and":2},"hook_time":0.000024885,"search_time":0.000060297,"apply_time":0.000150431,"rebuild_time":8.44e-6,"total_time":0.000219304,"data":null,"n_rebuilds":0,"stop_reason":null},{"egraph_nodes":84,"egraph_classes":47,"applied":{"add.commute":6,"add.assoc":2,"mult.commute":6,"mult_2":2,"add_eq_prec":6,"mul_eq_prec":4,"xor_as_or_and":2,"int_distrib":5,"sub_to_neg":2},"hook_time":0.000032038,"search_time":0.00010672,"apply_time":0.000252806,"rebuild_time":0.00001309,"total_time":0.000372758,"data":null,"n_rebuilds":1,"stop_reason":null},{"egraph_nodes":139,"egraph_classes":66,"applied":{},"hook_time":0.000024316,"search_time":4.7e-8,"apply_time":4.4e-8,"rebuild_time":6.182e-6,"total_time":6.598e-6,"data":null,"n_rebuilds":0,"stop_reason":{"Other":"Found equivalence"}}]},"AddSub_1164":{"summary":{"iterations":3,"stop_reason":{"Other":"Found equivalence"},"egraph_nodes":56,"egraph_classes":28,"memo_size":65,"rebuilds":6,"total_time":0.00030940599999999997,"search_time":0.00008229799999999999,"apply_time":0.00020349799999999998,"rebuild_time":0.000022688},"iteration_info":[{"egraph_nodes":15,"egraph_classes":14,"applied":{"add.commute":1,"bw_0":1,"add_eq_prec":1,"diff_left_eq_prec":1,"diff_right_eq_prec":2,"add_as_xor_and":1,"sub_to_neg":2,"gt-lt":1},"hook_time":0.000018416,"search_time":0.000034039,"apply_time":0.000046528,"rebuild_time":6.03e-6,"total_time":0.000086756,"data":null,"n_rebuilds":2,"stop_reason":null},{"egraph_nodes":36,"egraph_classes":23,"applied":{"add.commute":4,"add.assoc":1,"mult.commute":2,"mult_2":1,"add_0":1,"add_eq_prec":3,"diff_left_eq_prec":1,"add_as_xor_and":1,"xor_as_or_and":1,"Num.ring_1_class.mult_minus1-rev":1,"sub_to_neg":3},"hook_time":0.000016063,"search_time":0.0000482,"apply_time":0.000156855,"rebuild_time":0.000012056,"total_time":0.000217328,"data":null,"n_rebuilds":4,"stop_reason":null},{"egraph_nodes":65,"egraph_classes":28,"applied":{},"hook_time":0.000025433,"search_time":5.9e-8,"apply_time":1.15e-7,"rebuild_time":4.602e-6,"total_time":5.322e-6,"data":null,"n_rebuilds":0,"stop_reason":{"Other":"Found equivalence"}}]}}